MANIFEST.in
README.md
setup.cfg
setup.py
dynash/__init__.py
dynash/dynash.py
dynash/version.py
dynash.egg-info/PKG-INFO
dynash.egg-info/SOURCES.txt
dynash.egg-info/dependency_links.txt
dynash.egg-info/entry_points.txt
dynash.egg-info/requires.txt
dynash.egg-info/top_level.txt
dynash2/__init__.py
dynash2/dynash2.py
dynash2/list.py
dynash2/version.py