Metadata-Version: 1.1
Name: dynash
Version: 0.9.8
Summary: Command line client for DynamoDB
Home-page: https://github.com/raff/dynash
Author: Raffaele Sena
Author-email: raff367@gmail.com
License: MIT
Platform: Posix; MacOS X; Windows
Classifier: Development Status :: 4 - Beta
Classifier: Environment :: Console
Classifier: Intended Audience :: Developers
Classifier: License :: OSI Approved :: MIT License
Classifier: Operating System :: OS Independent
Classifier: Topic :: Internet
Classifier: Topic :: Utilities
Classifier: Programming Language :: Python :: 2
Classifier: Programming Language :: Python :: 2.6
Classifier: Programming Language :: Python :: 2.7
